pathfind/__init__.py
pathfind/finder/__init__.py
pathfind/finder/finder.py
pathfind/finder/queue.py
pathfind/finder/tool.py
pathfind/finder/alg/__init__.py
pathfind/finder/alg/a_star.py
pathfind/finder/alg/breadth_first_search.py
pathfind/finder/alg/d_star_lite.py
pathfind/finder/alg/depth_first_search.py
pathfind/finder/alg/dijkstra.py
pathfind/finder/alg/greedy_best_first.py
pathfind/finder/alg/jump_point_search.py
pathfind/graph/__init__.py
pathfind/graph/edge.py
pathfind/graph/graph.py
pathfind/graph/node.py
pathfind/graph/portable.py
pathfind/graph/transform.py
pathfind-0.1.2.dist-info/LICENSE
pathfind-0.1.2.dist-info/METADATA
pathfind-0.1.2.dist-info/WHEEL
pathfind-0.1.2.dist-info/top_level.txt
pathfind-0.1.2.dist-info/RECORD
