Metadata-Version: 2.1
Name: pathfind
Version: 0.1.2
Summary: path finding algorithms in python
Home-page: https://github.com/MorvanZhou/pathfind
Author: MorvanZhou
Author-email: morvanzhou@hotmail.com
Project-URL: Bug Tracker, https://github.com/MorvanZhou/pathfind/issues
Project-URL: Source, https://github.com/MorvanZhou/pathfind
Classifier: Programming Language :: Python :: 3
Classifier: License :: OSI Approved :: MIT License
Classifier: Operating System :: OS Independent
Requires-Python: >=3.7
License-File: LICENSE
Requires-Dist: matplotlib >=3.3.4
Requires-Dist: igraph >=0.10.2
Provides-Extra: build
Requires-Dist: tox ==3.24.3 ; extra == 'build'
Requires-Dist: tox-conda ; extra == 'build'
Requires-Dist: build ; extra == 'build'
Requires-Dist: twine ; extra == 'build'
Requires-Dist: pylint ; extra == 'build'
Requires-Dist: line-profiler ; extra == 'build'
